<?xml version="1.0" encoding="UTF-8"?>
<beans xmlns="http://www.springframework.org/schema/beans"
       xmlns:xsi="http://www.w3.org/2001/XMLSchema-instance"
       xmlns:context="http://www.springframework.org/schema/context" xmlns:tx="http://www.springframework.org/schema/tx"
       xmlns:aop="http://www.springframework.org/schema/aop"
       xsi:schemaLocation="http://www.springframework.org/schema/beans http://www.springframework.org/schema/beans/spring-beans.xsd http://www.springframework.org/schema/context http://www.springframework.org/schema/context/spring-context.xsd http://www.springframework.org/schema/tx http://www.springframework.org/schema/tx/spring-tx.xsd http://www.springframework.org/schema/aop http://www.springframework.org/schema/aop/spring-aop.xsd">

    <context:annotation-config/>
    <context:component-scan base-package="com.yangyang" />

    <bean id="helloworld" class="com.yangyang.quartz.HelloWorld" />
    <bean id="jobDetail" class="org.springframework.scheduling.quartz.MethodInvokingJobDetailFactoryBean">
        <property name="targetObject" ref="helloworld" />
        <property name="targetMethod" value="sayHello" />
    </bean>


    <bean id="mailSender" class="org.springframework.mail.javamail.JavaMailSenderImpl">
        <property name="host" value="smtp.qq.com"/>
        <property name="port" value="465"/>
        <property name="protocol" value="smtp"/>
        <property name="username" value="yangyang20666"/>
        <property name="password" value="gdetbggcpkdnhijd"/>
        <property name="javaMailProperties">
            <props>
                <prop key="mail.smtp.auth">true</prop>
                <prop key="mail.smtp.socketFactory.class">javax.net.ssl.SSLSocketFactory</prop>
            </props>
        </property>
    </bean>

    <bean id="setting" class="org.springframework.beans.factory.config.PropertiesFactoryBean">
        <property name="locations">
            <list>
                <value>classpath:auth.properties</value>
            </list>
        </property>
        <!-- 设置编码格式 -->
        <property name="fileEncoding" value="UTF-8"></property>
    </bean>
    <!--1: 配置 mysql-->
    <context:property-placeholder location="classpath:jdbc.properties"/>
    <bean id="dataSource" class="org.apache.commons.dbcp.BasicDataSource" destroy-method="close">
        <property name="driverClassName" value="${jdbc.driverClassName}"/>
        <property name="url" value="${jdbc.url}"/>
        <property name="username" value="${jdbc.username}"/>
        <property name="password" value="${jdbc.password}"/>
        <property name="initialSize" value="1" />
        <property name="minIdle" value="1" />
        <property name="maxActive" value="100" />
        <property name="maxIdle" value="20" />
        <property name="maxWait" value="1000" />
    </bean>
    <!-- hibernate 配置 -->
    <bean id="sessionFactory" class="org.springframework.orm.hibernate5.LocalSessionFactoryBean">
        <property name="dataSource" ref="dataSource" />
        <property name="packagesToScan">
            <value>com.yangyang.model</value>
        </property>
        <property name="hibernateProperties">
            <props>
                <prop key="hibernate.dialect">org.hibernate.dialect.MySQL5InnoDBDialect</prop>
                <prop key="hibernate.show_sql">true</prop>
                <prop key="hibernate.format_sql">true</prop>
                <prop key="hibernate.hbm2ddl.auto">update</prop>
            </props>
        </property>
    </bean>

    <!-- 3: 配置事务管理器 -->
    <bean id="transactionManager"
          class="org.springframework.orm.hibernate5.HibernateTransactionManager">
        <property name="sessionFactory" ref="sessionFactory"/>
    </bean>
    <!-- 4: 配置支持注解的事物 -->
    <!--<tx:annotation-driven transaction-manager="transactionManager"/>-->

    <tx:advice id="txAdivce" transaction-manager="transactionManager">
        <tx:attributes>
            <tx:method name="del*" propagation="REQUIRED"/>
            <tx:method name="update*" propagation="REQUIRED"/>
            <tx:method name="save*" propagation="REQUIRED"/>
            <tx:method name="add*" propagation="REQUIRED"/>
            <tx:method name="*" read-only="true"/>
        </tx:attributes>
    </tx:advice>
    <!-- 配置事务切入点 -->
    <aop:config>
        <aop:pointcut id="pointcut" expression="execution(* com.yangyang.service.iservice.*.*(..))"/>
        <aop:advisor advice-ref="txAdivce" pointcut-ref="pointcut"/>
    </aop:config>

</beans>